[
  {
    "title": "Economic Backwardness and Economic Growth",
    "authors": "Leibenstein",
    "year": 1957,
    "stratum": "theory-foundational",
    "candidate_hint": null,
    "verdict": "TITLE_KEY",
    "final_doi": null,
    "reason": "book/chapter, no DOI"
  },
  {
    "title": "Peasants, Procreation, and Pensions",
    "authors": "Neher",
    "year": 1971,
    "stratum": "theory-foundational",
    "candidate_hint": null,
    "verdict": "TITLE_KEY",
    "final_doi": null,
    "reason": "book/chapter, no DOI"
  },
  {
    "title": "The Old Age Security Hypothesis and Population Growth",
    "authors": "Willis",
    "year": 1980,
    "stratum": "theory-foundational",
    "candidate_hint": null,
    "verdict": "TITLE_KEY",
    "final_doi": null,
    "reason": "book/chapter, no DOI"
  },
  {
    "title": "The Old-Age Security Motive for Fertility",
    "authors": "Nugent",
    "year": 1985,
    "stratum": "theory-foundational",
    "candidate_hint": "10.2307/1973379",
    "verdict": "VERIFIED",
    "final_doi": "10.2307/1973379",
    "via": "hint",
    "jaccard": 1.0,
    "crossref_title": "The Old-Age Security Motive for Fertility",
    "crossref_year": 1985,
    "venue": "Population and Development Review"
  },
  {
    "title": "Toward a Restatement of Demographic Transition Theory",
    "authors": "Caldwell",
    "year": 1976,
    "stratum": "theory-foundational",
    "candidate_hint": "10.2307/1971615",
    "verdict": "VERIFIED",
    "final_doi": "10.2307/1971615",
    "via": "hint",
    "jaccard": 1.0,
    "crossref_title": "Toward A Restatement of Demographic Transition Theory",
    "crossref_year": 1976,
    "venue": "Population and Development Review"
  },
  {
    "title": "A Reformulation of the Economic Theory of Fertility",
    "authors": "Becker; Barro",
    "year": 1988,
    "stratum": "theory-formal",
    "candidate_hint": "10.2307/1882640",
    "verdict": "VERIFIED",
    "final_doi": "10.2307/1882640",
    "via": "hint",
    "jaccard": 1.0,
    "crossref_title": "A Reformulation of the Economic Theory of Fertility",
    "crossref_year": 1988,
    "venue": "The Quarterly Journal of Economics"
  },
  {
    "title": "Fertility Choice in a Model of Economic Growth",
    "authors": "Barro; Becker",
    "year": 1989,
    "stratum": "theory-formal",
    "candidate_hint": "10.2307/1912563",
    "verdict": "VERIFIED",
    "final_doi": "10.2307/1912563",
    "via": "hint",
    "jaccard": 1.0,
    "crossref_title": "Fertility Choice in a Model of Economic Growth",
    "crossref_year": 1989,
    "venue": "Econometrica"
  },
  {
    "title": "Intergenerational Trade, Longevity, and Economic Growth",
    "authors": "Ehrlich; Lui",
    "year": 1991,
    "stratum": "theory-formal",
    "candidate_hint": "10.1086/261788",
    "verdict": "VERIFIED",
    "final_doi": "10.1086/261788",
    "via": "hint",
    "jaccard": 1.0,
    "crossref_title": "Intergenerational Trade, Longevity, and Economic Growth",
    "crossref_year": 1991,
    "venue": "Journal of Political Economy"
  },
  {
    "title": "Pay-as-you-go public pensions with endogenous fertility",
    "authors": "Nishimura; Zhang",
    "year": 1992,
    "stratum": "theory-formal",
    "candidate_hint": "10.1016/0047-2727(92)90029-F",
    "verdict": "VERIFIED",
    "final_doi": "10.1016/0047-2727(92)90029-f",
    "via": "hint",
    "jaccard": 1.0,
    "crossref_title": "Pay-as-you-go public pensions with endogenous fertility",
    "crossref_year": 1992,
    "venue": "Journal of Public Economics"
  },
  {
    "title": "Intergenerational transfers without altruism: Family, market and state",
    "authors": "Cigno",
    "year": 1993,
    "stratum": "theory-formal",
    "candidate_hint": "10.1016/0176-2680(93)90036-T",
    "hint_failed": "J=0.57 yr 1993 -> Intergenerational transfers without altruism",
    "verdict": "VERIFIED",
    "final_doi": "10.1016/0176-2680(93)90036-t",
    "via": "manual (verifier FN: subtitle dropped)",
    "crossref_title": "Intergenerational transfers without altruism",
    "crossref_year": 1993,
    "venue": "European Journal of Political Economy",
    "jaccard": 0.57
  },
  {
    "title": "Pay-as-you-go financed public pensions in a model of endogenous growth and fertility",
    "authors": "Wigger",
    "year": 1999,
    "stratum": "theory-formal",
    "candidate_hint": "10.1007/s001480050116",
    "hint_failed": "J=0.00 yr 1999 -> Social security, social welfare and the aging popu",
    "verdict": "VERIFIED",
    "via": "search",
    "final_doi": "10.1007/s001480050117",
    "jaccard": 1.0,
    "crossref_title": "Pay-as-you-go financed public pensions in a model of endogenous growth and fertility",
    "crossref_year": 1999,
    "venue": "Journal of Population Economics"
  },
  {
    "title": "Mortality, Fertility, and Saving in a Malthusian Economy",
    "authors": "Boldrin; Jones",
    "year": 2002,
    "stratum": "theory-formal",
    "candidate_hint": "10.1006/redy.2002.0186",
    "verdict": "VERIFIED",
    "final_doi": "10.1006/redy.2002.0186",
    "via": "hint",
    "jaccard": 1.0,
    "crossref_title": "Mortality, Fertility, and Saving in a Malthusian Economy",
    "crossref_year": 2002,
    "venue": "Review of Economic Dynamics"
  },
  {
    "title": "The pay-as-you-go pension system as fertility insurance and an enforcement device",
    "authors": "Sinn",
    "year": 2004,
    "stratum": "theory-formal",
    "candidate_hint": "10.1016/S0047-2727(03)00015-X",
    "verdict": "VERIFIED",
    "final_doi": "10.1016/s0047-2727(03)00015-x",
    "via": "hint",
    "jaccard": 1.0,
    "crossref_title": "The pay-as-you-go pension system as fertility insurance and an enforcement device",
    "crossref_year": 2004,
    "venue": "Journal of Public Economics"
  },
  {
    "title": "Fertility and Social Security",
    "authors": "Boldrin; De Nardi; Jones",
    "year": 2015,
    "stratum": "theory-formal",
    "candidate_hint": "10.1017/dem.2015.4",
    "hint_failed": "J=0.00 yr 2015 -> A CLOSED-FORM SOLUTION FOR THE HEALTH CAPITAL MODE",
    "verdict": "VERIFIED",
    "via": "search",
    "final_doi": "10.1017/dem.2014.14",
    "jaccard": 1.0,
    "crossref_title": "FERTILITY AND SOCIAL SECURITY",
    "crossref_year": 2015,
    "venue": "Journal of Demographic Economics"
  },
  {
    "title": "Children and Pensions",
    "authors": "Cigno; Werding",
    "year": 2007,
    "stratum": "theory-formal",
    "candidate_hint": null,
    "verdict": "TITLE_KEY",
    "final_doi": null,
    "reason": "book/chapter, no DOI"
  },
  {
    "title": "Risk and Insurance: Perspectives on Fertility and Agrarian Change in India and Bangladesh",
    "authors": "Cain",
    "year": 1981,
    "stratum": "empirical-classic",
    "candidate_hint": "10.2307/1972894",
    "hint_failed": "J=0.07 yr 1983 -> On Kinship Structure, Female Autonomy, and Demogra",
    "verdict": "VERIFIED",
    "via": "search",
    "final_doi": "10.2307/1972559",
    "jaccard": 1.0,
    "crossref_title": "Risk and Insurance: Perspectives on Fertility and Agrarian Change in India and Bangladesh",
    "crossref_year": 1981,
    "venue": "Population and Development Review"
  },
  {
    "title": "Fertility as an Adjustment to Risk",
    "authors": "Cain",
    "year": 1983,
    "stratum": "empirical-classic",
    "candidate_hint": "10.2307/1973326",
    "hint_failed": "J=0.00 yr 1983 -> Prosperity and Misery in Modern Bengal: The Famine",
    "verdict": "VERIFIED",
    "via": "search",
    "final_doi": "10.2307/1973546",
    "jaccard": 1.0,
    "crossref_title": "Fertility as an Adjustment to Risk",
    "crossref_year": 1983,
    "venue": "Population and Development Review"
  },
  {
    "title": "Social Security and Fertility: An International Perspective",
    "authors": "Hohm",
    "year": 1975,
    "stratum": "empirical-classic",
    "candidate_hint": "10.2307/2060719",
    "hint_failed": "J=0.00 yr 1975 -> A method for the estimation of fecundability",
    "verdict": "VERIFIED",
    "via": "search",
    "final_doi": "10.2307/2060718",
    "jaccard": 1.0,
    "crossref_title": "Social security and fertility: An international perspective",
    "crossref_year": 1975,
    "venue": "Demography"
  },
  {
    "title": "Fertility and Pension Programs in LDCs: A Model of Mutual Reinforcement",
    "authors": "Entwisle; Winegarden",
    "year": 1984,
    "stratum": "empirical-classic",
    "candidate_hint": "10.1086/451530",
    "hint_failed": "J=0.00 yr 1986 -> Food Grain Policy in the Republic of Korea: The Ec",
    "verdict": "VERIFIED",
    "via": "search",
    "final_doi": "10.1086/451388",
    "jaccard": 1.0,
    "crossref_title": "Fertility and Pension Programs in LDCs: A Model of Mutual Reinforcement",
    "crossref_year": 1984,
    "venue": "Economic Development and Cultural Change"
  },
  {
    "title": "Old Age Pensions and Fertility in Rural Areas of Less Developed Countries: Some Evidence from Mexico",
    "authors": "Nugent; Gillaspy",
    "year": 1983,
    "stratum": "empirical-classic",
    "candidate_hint": "10.1086/451353",
    "hint_failed": "J=0.00 yr 1983 -> Egypt's Development in the Seventies",
    "verdict": "VERIFIED",
    "via": "search",
    "final_doi": "10.1086/451359",
    "jaccard": 1.0,
    "crossref_title": "Old Age Pensions and Fertility in Rural Areas of Less Developed Countries: Some Evidence from Mexico",
    "crossref_year": 1983,
    "venue": "Economic Development and Cultural Change"
  },
  {
    "title": "The effects of financial markets and social security on saving and fertility behaviour in Italy",
    "authors": "Cigno; Rosati",
    "year": 1992,
    "stratum": "empirical-classic",
    "candidate_hint": "10.1007/BF00163065",
    "hint_failed": "J=0.00 yr 1992 -> Call for papers",
    "verdict": "VERIFIED",
    "via": "search",
    "final_doi": "10.1007/bf00163064",
    "jaccard": 1.0,
    "crossref_title": "The effects of financial markets and social security on saving and fertility behaviour in Italy",
    "crossref_year": 1992,
    "venue": "Journal of Population Economics"
  },
  {
    "title": "Jointly determined saving and fertility behaviour: Theory, and estimates for Germany, Italy, UK and USA",
    "authors": "Cigno; Rosati",
    "year": 1996,
    "stratum": "empirical-classic",
    "candidate_hint": "10.1016/0014-2921(95)00035-6",
    "hint_failed": "J=0.00 yr 1996 -> Minimum wage unemployment and growth",
    "verdict": "VERIFIED",
    "via": "search",
    "final_doi": "10.1016/0014-2921(95)00046-1",
    "jaccard": 1.0,
    "crossref_title": "Jointly determined saving and fertility behaviour: Theory, and estimates for Germany, Italy, UK and USA",
    "crossref_year": 1996,
    "venue": "European Economic Review"
  },
  {
    "title": "An Economic Analysis of Fertility",
    "authors": "Becker",
    "year": 1960,
    "stratum": "theory-foundational",
    "candidate_hint": null,
    "verdict": "TITLE_KEY",
    "final_doi": null,
    "reason": "book/chapter, no DOI"
  },
  {
    "title": "The old age security hypothesis and optimal population growth",
    "authors": "Bental",
    "year": 1989,
    "stratum": "theory-formal",
    "candidate_hint": "10.1007/BF00522411",
    "hint_failed": "J=0.00 yr 1960 -> Das Wachstum der Chorionzotten vom II. bis X. Mona",
    "verdict": "VERIFIED",
    "via": "search",
    "final_doi": "10.1007/bf00166069",
    "jaccard": 1.0,
    "crossref_title": "The old age security hypothesis and optimal population growth",
    "crossref_year": 1989,
    "venue": "Journal of Population Economics"
  },
  {
    "title": "Endogenous fertility and optimal population size",
    "authors": "Eckstein; Wolpin",
    "year": 1985,
    "stratum": "theory-formal",
    "candidate_hint": "10.1016/0047-2727(85)90020-1",
    "hint_failed": "crossref 404",
    "verdict": "VERIFIED",
    "via": "search",
    "final_doi": "10.1016/0047-2727(85)90030-1",
    "jaccard": 1.0,
    "crossref_title": "Endogenous fertility and optimal population size",
    "crossref_year": 1985,
    "venue": "Journal of Public Economics"
  },
  {
    "title": "Endogenous fertility, altruistic behavior across generations, and social security systems",
    "authors": "Prinz",
    "year": 1990,
    "stratum": "theory-formal",
    "candidate_hint": "10.1007/BF00163071",
    "hint_failed": "J=0.00 yr 1993 -> Seventh ESPE Congress and General Assembly in Buda",
    "verdict": "VERIFIED",
    "via": "search",
    "final_doi": "10.1007/bf00163074",
    "jaccard": 1.0,
    "crossref_title": "Endogenous fertility, altruistic behavior across generations, and social security systems",
    "crossref_year": 1990,
    "venue": "Journal of Population Economics"
  },
  {
    "title": "Social security and endogenous growth",
    "authors": "Zhang",
    "year": 1995,
    "stratum": "theory-formal",
    "candidate_hint": "10.1016/0047-2727(94)01473-2",
    "verdict": "VERIFIED",
    "final_doi": "10.1016/0047-2727(94)01473-2",
    "via": "hint",
    "jaccard": 1.0,
    "crossref_title": "Social security and endogenous growth",
    "crossref_year": 1995,
    "venue": "Journal of Public Economics"
  },
  {
    "title": "Social security in a non-altruistic model with uncertainty and endogenous fertility",
    "authors": "Rosati",
    "year": 1996,
    "stratum": "theory-formal",
    "candidate_hint": "10.1016/0047-2727(95)01524-8",
    "hint_failed": "J=0.00 yr 1996 -> Labour supply, household production and intra-fami",
    "verdict": "VERIFIED",
    "via": "search",
    "final_doi": "10.1016/0047-2727(95)01513-2",
    "jaccard": 1.0,
    "crossref_title": "Social security in a non-altruistic model with uncertainty and endogenous fertility",
    "crossref_year": 1996,
    "venue": "Journal of Public Economics"
  },
  {
    "title": "Social security and endogenous fertility: pensions and child allowances as siamese twins",
    "authors": "van Groezen; Leers; Meijdam",
    "year": 2003,
    "stratum": "theory-formal",
    "candidate_hint": "10.1016/S0047-2727(01)00134-7",
    "verdict": "VERIFIED",
    "final_doi": "10.1016/s0047-2727(01)00134-7",
    "via": "hint",
    "jaccard": 1.0,
    "crossref_title": "Social security and endogenous fertility: pensions and child allowances as siamese twins",
    "crossref_year": 2003,
    "venue": "Journal of Public Economics"
  },
  {
    "title": "How does social security affect economic growth? Evidence from cross-country data",
    "authors": "Zhang; Zhang",
    "year": 2004,
    "stratum": "theory-formal",
    "candidate_hint": "10.1007/s00148-004-0198-x",
    "verdict": "VERIFIED",
    "final_doi": "10.1007/s00148-004-0198-x",
    "via": "hint",
    "jaccard": 1.0,
    "crossref_title": "How does social security affect economic growth? Evidence from cross-country data",
    "crossref_year": 2004,
    "venue": "Population Economics"
  },
  {
    "title": "Pensions and fertility incentives",
    "authors": "Fenge; Meier",
    "year": 2005,
    "stratum": "theory-formal",
    "candidate_hint": "10.1111/j.0008-4085.2005.00268.x",
    "hint_failed": "J=0.00 yr 2005 -> A tale of two cities and a Giffen good",
    "verdict": "VERIFIED",
    "via": "search",
    "final_doi": "10.2139/ssrn.385783",
    "jaccard": 1.0,
    "crossref_title": "Pensions and Fertility Incentives",
    "crossref_year": 2003,
    "venue": "SSRN Electronic Journal"
  },
  {
    "title": "Social security and demographic trends: Theory and evidence from the international experience",
    "authors": "Ehrlich; Kim",
    "year": 2007,
    "stratum": "theory-formal",
    "candidate_hint": "10.1016/j.red.2006.09.003",
    "hint_failed": "J=0.00 yr 2007 -> The impact of disembodied technological progress o",
    "verdict": "VERIFIED",
    "via": "search",
    "final_doi": "10.1016/j.red.2006.09.002",
    "jaccard": 1.0,
    "crossref_title": "Social security and demographic trends: Theory and evidence from the international experience",
    "crossref_year": 2007,
    "venue": "Review of Economic Dynamics"
  },
  {
    "title": "Are family allowances and fertility-related pensions perfect substitutes?",
    "authors": "Fenge; Meier",
    "year": 2009,
    "stratum": "theory-formal",
    "candidate_hint": "10.1007/s10797-008-9079-7",
    "hint_failed": "J=0.00 yr 2008 -> A positive analysis of labor-market institutions a",
    "verdict": "VERIFIED",
    "via": "search",
    "final_doi": "10.1007/s10797-007-9060-x",
    "jaccard": 1.0,
    "crossref_title": "Are family allowances and fertility-related pensions perfect substitutes?",
    "crossref_year": 2008,
    "venue": "International Tax and Public Finance"
  },
  {
    "title": "Fertility, child care outside the home, and pay-as-you-go social security",
    "authors": "Hirazawa; Yakita",
    "year": 2009,
    "stratum": "theory-formal",
    "candidate_hint": "10.1007/s00148-008-0214-7",
    "hint_failed": "J=0.00 yr 2008 -> Hiring older workers and employing older workers: ",
    "verdict": "VERIFIED",
    "via": "search",
    "final_doi": "10.1007/s00148-007-0153-8",
    "jaccard": 1.0,
    "crossref_title": "Fertility, child care outside the home, and pay-as-you-go social security",
    "crossref_year": 2007,
    "venue": "Journal of Population Economics"
  },
  {
    "title": "Optimal social security in a dynastic model with human capital externalities, fertility and endogenous growth",
    "authors": "Yew; Zhang",
    "year": 2009,
    "stratum": "theory-formal",
    "candidate_hint": "10.1016/j.jpubeco.2009.02.006",
    "hint_failed": "J=0.00 yr 2009 -> Family background and income during the rise of th",
    "verdict": "VERIFIED",
    "via": "search",
    "final_doi": "10.1016/j.jpubeco.2008.10.005",
    "jaccard": 1.0,
    "crossref_title": "Optimal social security in a dynastic model with human capital externalities, fertility and endogenous growth",
    "crossref_year": 2009,
    "venue": "Journal of Public Economics"
  },
  {
    "title": "Pensions with endogenous and stochastic fertility",
    "authors": "Cremer; Gahvari; Pestieau",
    "year": 2008,
    "stratum": "theory-formal",
    "candidate_hint": "10.1016/j.jpubeco.2008.07.001",
    "hint_failed": "J=0.00 yr 2009 -> Community rating and the market for private non-gr",
    "verdict": "VERIFIED",
    "via": "search",
    "final_doi": "10.1016/j.jpubeco.2006.03.007",
    "jaccard": 1.0,
    "crossref_title": "Pensions with endogenous and stochastic fertility",
    "crossref_year": 2006,
    "venue": "Journal of Public Economics"
  },
  {
    "title": "An econometric analysis of the old-age security motive for childbearing",
    "authors": "Jensen",
    "year": 1990,
    "stratum": "empirical-classic",
    "candidate_hint": "10.2307/2527025",
    "hint_failed": "J=0.00 yr 1990 -> Estimating the Intrahousehold Incidence of Illness",
    "verdict": "VERIFIED",
    "via": "search",
    "final_doi": "10.2307/2527024",
    "jaccard": 1.0,
    "crossref_title": "An Econometric Analysis of the Old-Age Security Motive for Childbearing",
    "crossref_year": 1990,
    "venue": "International Economic Review"
  },
  {
    "title": "An Old-Age Security Motive for Fertility in the United States?",
    "authors": "Rendall; Bahchieva",
    "year": 1998,
    "stratum": "empirical-classic",
    "candidate_hint": "10.2307/2807975",
    "verdict": "VERIFIED",
    "final_doi": "10.2307/2807975",
    "via": "hint",
    "jaccard": 1.0,
    "crossref_title": "An Old-Age Security Motive for Fertility in the United States?",
    "crossref_year": 1998,
    "venue": "Population and Development Review"
  },
  {
    "title": "Investing for the old age: pensions, children and savings",
    "authors": "Galasso; Gatti; Profeta",
    "year": 2009,
    "stratum": "empirical-classic",
    "candidate_hint": "10.1007/s10797-009-9105-4",
    "hint_failed": "J=0.00 yr 2009 -> Native welfare losses from high skilled immigratio",
    "verdict": "VERIFIED",
    "via": "search",
    "final_doi": "10.2139/ssrn.1338058",
    "jaccard": 1.0,
    "crossref_title": "Investing for the Old Age: Pensions, Children and Savings",
    "crossref_year": 2008,
    "venue": "SSRN Electronic Journal"
  },
  {
    "title": "The Impact of Social Security on Saving and Fertility in Germany",
    "authors": "Cigno; Casolaro; Rosati",
    "year": 2003,
    "stratum": "empirical-classic",
    "candidate_hint": "10.1628/0015221032500864",
    "hint_failed": "crossref 404",
    "verdict": "VERIFIED",
    "via": "search",
    "final_doi": "10.1628/0015221032643209",
    "jaccard": 1.0,
    "crossref_title": "The Impact of Social Security on Saving and Fertility in Germany",
    "crossref_year": 2003,
    "venue": "FinanzArchiv"
  }
]